aquaref/library/metro/net40/MetroFramework.Design.dll
aquaref/library/metro/net40/MetroFramework.dll
aquaref/library/metro/net40/MetroFramework.Fonts.dll
aquaref/library/metro.py
aquaref/test.metro.1.py
aquaref/winforms/metro/__init__.py
aquaref/winforms/metro/metro_animationbase.py
aquaref/winforms/metro/metro_button.py
aquaref/winforms/metro/metro_color_style.txt
aquaref/winforms/metro/metro_control.py
aquaref/winforms/metro/metro_form.py
aquaref/winforms/metro/metro_form.txt
aquaref/winforms/metro/metro_label.py
aquaref/winforms/metro/metro_messagebox.py
aquaref/winforms/metro/metro_panel.py
aquaref/winforms/metro/metro_style_manager.py
aquaref/winforms/metro/metro_style_manager.txt
aquaref/winforms/metro/metro_tab_control.py
aquaref/winforms/metro/metro_tab_page.py
aquaref/winforms/metro/metro_tooltip.py
aquaref_metroframework-0.1.2.dist-info/METADATA
aquaref_metroframework-0.1.2.dist-info/WHEEL
aquaref_metroframework-0.1.2.dist-info/RECORD
